solutions_template/__init__.py
solutions_template/cli/__init__.py
solutions_template/cli/cli.py
solutions_template/cli/cli_utils.py
solutions_template/cli/component.py
solutions_template/cli/infra.py
solutions_template/cli/set.py
solutions_template/cli/template.py
solutions_template/copier_extensions/__init__.py
solutions_template/copier_extensions/st_helpers.py
solutions_template/module_template/.st/module_answers/{{'{{component_name}}'}}.yaml
solutions_template/module_template/README.md
solutions_template/module_template/copier.yaml
solutions_template/module_template/docs/components/{{'{{component_name}}'}}.md
solutions_template/module_template/template_copier.yaml
"solutions_template/module_template/{{""{{'.github' if use_github_action}}""}}/workflows/{{""unit_test_linter_{{component_name}}""}}.yaml"
solutions_template/module_template/{{'components' if has_component}}/{{'{{component_name}}'}}/Dockerfile
solutions_template/module_template/{{'components' if has_component}}/{{'{{component_name}}'}}/requirements.txt
solutions_template/module_template/{{'components' if has_component}}/{{'{{component_name}}'}}/skaffold.yaml
solutions_template/module_template/{{'components' if has_component}}/{{'{{component_name}}'}}/src/main.py
solutions_template/module_template/{{'components' if has_component}}/{{'{{component_name}}'}}/st_module.yaml
solutions_template/module_template/{{'terraform' if has_terraform_stage}}/stages/{{terraform_stage if has_terraform_stage}}/backend.tf
solutions_template/module_template/{{'terraform' if has_terraform_stage}}/stages/{{terraform_stage if has_terraform_stage}}/main.tf
solutions_template/module_template/{{'terraform' if has_terraform_stage}}/stages/{{terraform_stage if has_terraform_stage}}/providers.tf
solutions_template/module_template/{{'terraform' if has_terraform_stage}}/stages/{{terraform_stage if has_terraform_stage}}/terraform.tfvars
solutions_template-1.14.0.dist-info/LICENSE
solutions_template-1.14.0.dist-info/METADATA
solutions_template-1.14.0.dist-info/WHEEL
solutions_template-1.14.0.dist-info/entry_points.txt
solutions_template-1.14.0.dist-info/RECORD
