Metadata-Version: 2.1
Name: solutions-template
Version: 1.14.0
Summary: A solution framework to generate a project with built-in structure and modules
Home-page: https://github.com/GoogleCloudPlatform/solutions-template
License: Apache
Author: Jon Chen
Author-email: jonchen@google.com
Requires-Python: >=3.8,<4.0
Classifier: License :: Other/Proprietary License
Classifier: Programming Language :: Python :: 3
Classifier: Programming Language :: Python :: 3.8
Classifier: Programming Language :: Python :: 3.9
Classifier: Programming Language :: Python :: 3.10
Classifier: Programming Language :: Python :: 3.11
Requires-Dist: copier (>=7.2.0,<8.0.0)
Requires-Dist: copier-templates-extensions (>=0.3.0,<0.4.0)
Requires-Dist: jinja2 (>=3.1.2,<4.0.0)
Requires-Dist: jinja2-strcase (>=0.0.2,<0.0.3)
Requires-Dist: jinja2-time (>=0.2.0,<0.3.0)
Requires-Dist: pathlib (>=1.0.1,<2.0.0)
Requires-Dist: pyyaml (>=6.0,<7.0)
Requires-Dist: typer (>=0.9.0,<0.10.0)
Project-URL: Repository, https://github.com/GoogleCloudPlatform/solutions-template
